README.md
setup.py
openapi_schema_to_json_schema/__init__.py
openapi_schema_to_json_schema/to_jsonschema.py
py_openapi_schema_to_json_schema.egg-info/PKG-INFO
py_openapi_schema_to_json_schema.egg-info/SOURCES.txt
py_openapi_schema_to_json_schema.egg-info/dependency_links.txt
py_openapi_schema_to_json_schema.egg-info/top_level.txt