Metadata-Version: 1.1
Name: py-openapi-schema-to-json-schema
Version: 0.0.1
Summary: translate openapi schemas to json schemas
Home-page: https://github.com/pglass/py-openapi-jsonschema-converter
Author: Paul Glass
Author-email: pnglass@gmail.com
License: UNKNOWN
Keywords: openapi json schema convert translate
Platform: UNKNOWN
Classifier: Development Status :: 4 - Beta
Classifier: Intended Audience :: Developers
Classifier: License :: OSI Approved :: MIT License
Classifier: Operating System :: OS Independent
Classifier: Programming Language :: Python :: 2.7
Classifier: Programming Language :: Python :: 3.5
Classifier: Programming Language :: Python :: 3.6
Classifier: Programming Language :: Python :: 3.7
